hack4u/__init__.py
hack4u/courses.py
hack4u/utils.py
TesseralHackProject-0.1.0.dist-info/METADATA
TesseralHackProject-0.1.0.dist-info/WHEEL
TesseralHackProject-0.1.0.dist-info/top_level.txt
TesseralHackProject-0.1.0.dist-info/RECORD
