Metadata-Version: 2.1
Name: TesseralHackProject
Version: 0.1.0
Summary: Consultar cursos hack4u
Home-page: https://hack4u.io
Author: Tesseral
